ChangeLog.txt
MANIFEST.in
README.md
requirements.txt
setup.py
chineseregion/__init__.py
chineseregion/data.json
chineseregion/main.py
chineseregion.egg-info/PKG-INFO
chineseregion.egg-info/SOURCES.txt
chineseregion.egg-info/dependency_links.txt
chineseregion.egg-info/entry_points.txt
chineseregion.egg-info/top_level.txt