Metadata-Version: 1.1
Name: chineseregion
Version: 0.0.5
Summary: a chinese region lib for python
Home-page: UNKNOWN
Author: xuanwo
Author-email: xuanwo.cn@gmail.com
License: MIT License
Keywords: chinese,region,lib
Platform: UNKNOWN
Classifier: Development Status :: 3 - Alpha 
Classifier: Environment :: Console
Classifier: License :: OSI Approved :: MIT License
Classifier: Operating System :: MacOS
Classifier: Operating System :: POSIX
Classifier: Operating System :: POSIX :: Linux
Classifier: Operating System :: Microsoft
Classifier: Programming Language :: Python
Classifier: Programming Language :: Python :: 3
Classifier: Programming Language :: Python :: 3.5
